hyyap/__init__.py
hyyap/_hyymain.py
hyyap/font.py
hyyap/message.py
hyyap/Install/__init__.py
hyyap/Install/chrome.py
hyyap/Install/geek.py
hyyap/Install/git.py
hyyap/Install/huorong.py
hyyap/Install/innosetup.py
hyyap/Install/mingw.py
hyyap/Install/quark.py
hyyap/Install/vscode.py
hyyap/Install/vscpp.py
hyyap/Install/watttoolkit.py
hyyap/core/A.py
hyyap/core/B.py
hyyap/core/C.py
hyyap/core/DI.py
hyyap/core/S.py
hyyap/core/SY.py
hyyap/core/XH.py
hyyap/core/Z.py
hyyap/core/__init__.py
hyyap/utils/__init__.py
hyyap/utils/apopen.py
hyyap/utils/shared.py
hyyap/utils/timerun.py
hyyap-0.0.6.dist-info/LICENSE.txt
hyyap-0.0.6.dist-info/METADATA
hyyap-0.0.6.dist-info/WHEEL
hyyap-0.0.6.dist-info/entry_points.txt
hyyap-0.0.6.dist-info/top_level.txt
hyyap-0.0.6.dist-info/RECORD
